{
  "point": {
    "id": "002",
    "name": "Моремания Киевская",
    "yandex": "https://yandex.com/maps/org/moremaniya/145075891281/",
    "2gis": "https://2gis.ru/moscow/search/%D0%9C%D0%BE%D1%80%D0%B5%D0%BC%D0%B0%D0%BD%D0%B8%D1%8F%20%D0%9A%D0%B8%D0%B5%D0%B2%D1%81%D0%BA%D0%B0%D1%8F/firm/70000001112819901/37.563353%2C55.743326/tab/reviews?floor=building&m=37.563397%2C55.743306%2F17.61",
    "google": "https://www.google.com/maps/place/%D0%9C%D0%BE%D1%80%D0%B5%D0%BC%D0%B0%D0%BD%D0%B8%D1%8F/@55.7419085,37.558699,20z/data=!3m1!5s0x46b54b6b7cdd56f7:0x1ffd6e467ff38dc5!4m8!3m7!1s0x46b54b9f53d34899:0x7841b3ee5e3aeaa8!8m2!3d55.742002!4d37.5588587!9m1!1b1!16s%2Fg%2F11f5dygnz9?entry=ttu&g_ep=EgoyMDI2MDUxNy4wIKXMDSoASAFQAw%3D%3D"
  },
  "collectedAt": "2026-05-27T06:47:09.559Z",
  "reviewsCount": 4,
  "reviews": [
    {
      "id": "9623447408aaf895",
      "authorName": "Евгений Журбов",
      "rating": 1,
      "date": "5 мая 2026",
      "text": "2 июля приобрел том-ям и кальмарные щупальца. 3 июля я жестко отравился. Вызвал врача, сдал анализ, обнаружили кишечный вирус. Просто не рекомендую рисковать своим здоровьем. К сожалению, новое помещение не помогли выйти из проблем с стерильностью. Сведения переданы в роспотребнадзор.Читать целиком",
      "businessReply": null
    },
    {
      "id": "22b00eeccc6cea52",
      "authorName": "Иван Хмелев",
      "rating": 5,
      "date": "29 марта 2026",
      "text": "Отличный выбор свежих морепродуктов по приятным ценам. Быстрое и доброжелательное обслуживание. Очень ждали когда откроется на Киевской.",
      "businessReply": null
    },
    {
      "id": "64006b4649572809",
      "authorName": "Анастасия Макарова",
      "rating": 5,
      "date": "24 апреля 2026",
      "text": "Вкусная свежая еда, приятная обстановка, быстрое обслуживание и не много людей:) супер",
      "businessReply": null
    },
    {
      "id": "9cd701034d4b750e",
      "authorName": "Джейсон Стэтхэмов",
      "rating": 1,
      "date": "18 апреля 2026",
      "text": "Готовят не качество, а на количество, максимально экономят на начинке и порциях, по вкусу на 3-",
      "businessReply": null
    }
  ]
}